{
  "teams": [
    {
      "id": 1,
      "name": "Frankreich",
      "player1": "Trappi",
      "player2": "Nille"
    },
    {
      "id": 2,
      "name": "Brasilien",
      "player1": "Passi",
      "player2": "Jannik"
    },
    {
      "id": 3,
      "name": "Arsenal FC",
      "player1": "Langner",
      "player2": "Finn"
    },
    {
      "id": 4,
      "name": "Manchester City",
      "player1": "Stig",
      "player2": "Fabi"
    },
    {
      "id": 5,
      "name": "Deutschland",
      "player1": "Juglord",
      "player2": "Dominiek"
    },
    {
      "id": 6,
      "name": "Barcelona",
      "player1": "Bauer",
      "player2": "Knitter"
    }
  ]
}
